iotrans/__init__.py
iotrans/iotrans.py
iotrans-0.0.1.dist-info/LICENSE
iotrans-0.0.1.dist-info/METADATA
iotrans-0.0.1.dist-info/WHEEL
iotrans-0.0.1.dist-info/top_level.txt
iotrans-0.0.1.dist-info/RECORD
