Metadata-Version: 2.1
Name: iotrans
Version: 0.0.1
Summary: A package to easily convert structured data into various file formats
Home-page: https://github.com/open-data-toronto/iotrans
Author: Open Data Toronto
Author-email: opendata@toronto.ca
License: MIT
Platform: UNKNOWN
Classifier: Development Status :: 4 - Beta
Classifier: Environment :: Console
Classifier: Intended Audience :: Developers
Classifier: Intended Audience :: Science/Research
Classifier: Intended Audience :: System Administrators
Classifier: License :: OSI Approved :: MIT License
Classifier: Operating System :: OS Independent
Classifier: Programming Language :: Python :: 3
Classifier: Topic :: Scientific/Engineering
Requires-Dist: geopandas (>=0.4.0)
Requires-Dist: xmltodict (>=0.12.0)
